[
  {
    "CLIENTE - LUGAR VISITA": "Telemedellin ",
    "CIUDAD": "Medellín",
    "FECHA": 46036,
    "GESTOR LOGISTICO": "Julieth Higuita",
    "EJECUTADA": "SI",
    "ACTIVIDAD A REALIZAR POR EL GESTOR": "Se cuenta con acompañamiento del gestor",
    "SE GENERA ACOMPAÑAMIENTO ÁREA SGI": "Dayana Restrepo",
    "AREA": "SST",
    "ESTADO DE VISITA": "Ejecutada",
    "CANT. PERSONAL IMPACTADO": 6,
    "TEMAS ABORDADOS": "Inspección de vehículos, socialización de examenes, tamizajes de embriaguez"
  },
  {
    "CLIENTE - LUGAR VISITA": "Chemilab",
    "CIUDAD": "Medellín",
    "FECHA": 46037,
    "GESTOR LOGISTICO": "Edwin Aguirre",
    "EJECUTADA": "SI",
    "ACTIVIDAD A REALIZAR POR EL GESTOR": "Se cuenta con acompañamiento del gestor",
    "SE GENERA ACOMPAÑAMIENTO ÁREA SGI": "Farley Velandia",
    "AREA": "SST",
    "ESTADO DE VISITA": "Ejecutada",
    "CANT. PERSONAL IMPACTADO": 5,
    "TEMAS ABORDADOS": "Socializción Peligros y Riesgos, inspecciones  de parque automotor, tamizaje de alcohol."
  },
  {
    "CLIENTE - LUGAR VISITA": "Medicarte",
    "CIUDAD": "Medellín",
    "FECHA": 46038,
    "GESTOR LOGISTICO": "Sara Pasos",
    "EJECUTADA": "SI",
    "ACTIVIDAD A REALIZAR POR EL GESTOR": "Se cuenta con acompañamiento del gestor",
    "SE GENERA ACOMPAÑAMIENTO ÁREA SGI": "Farley Velandia",
    "AREA": "SST",
    "ESTADO DE VISITA": "Ejecutada",
    "CANT. PERSONAL IMPACTADO": 10,
    "TEMAS ABORDADOS": "Tamizaje de alcohol y verificación de condiciones de los vehículos inspecciones"
  },
  {
    "CLIENTE - LUGAR VISITA": "Jardin Botánico",
    "CIUDAD": "Medellín",
    "FECHA": 46038,
    "GESTOR LOGISTICO": "Yesid Carvajal",
    "EJECUTADA": "SI",
    "ACTIVIDAD A REALIZAR POR EL GESTOR": "Se cuenta con acompañamiento del gestor",
    "SE GENERA ACOMPAÑAMIENTO ÁREA SGI": "Dayana Restrepo",
    "AREA": "SST",
    "ESTADO DE VISITA": "Ejecutada",
    "CANT. PERSONAL IMPACTADO": 6,
    "TEMAS ABORDADOS": "Prevención del consumo de alcohol y drogras y Tamizajes"
  },
  {
    "CLIENTE - LUGAR VISITA": "EPM - Edificio inteligente",
    "CIUDAD": "Medellín",
    "FECHA": 46042,
    "GESTOR LOGISTICO": "Carlos Franco",
    "EJECUTADA": "SI",
    "ACTIVIDAD A REALIZAR POR EL GESTOR": "Sin acompañamiento del gestor",
    "SE GENERA ACOMPAÑAMIENTO ÁREA SGI": "Dayana Restrepo",
    "AREA": "SST",
    "ESTADO DE VISITA": "Ejecutada",
    "CANT. PERSONAL IMPACTADO": 3,
    "TEMAS ABORDADOS": "Prevención del consumo de alcohol y drogras y Tamizajes"
  },
  {
    "CLIENTE - LUGAR VISITA": "CAH - 123 Social",
    "CIUDAD": "Medellín",
    "FECHA": 46042,
    "GESTOR LOGISTICO": "Dayhana Sossa",
    "EJECUTADA": "SI",
    "ACTIVIDAD A REALIZAR POR EL GESTOR": "Se cuenta con acompañamiento del gestor",
    "SE GENERA ACOMPAÑAMIENTO ÁREA SGI": "Farley Velandia",
    "AREA": "SST",
    "ESTADO DE VISITA": "Ejecutada",
    "CANT. PERSONAL IMPACTADO": 6,
    "TEMAS ABORDADOS": "Inspección Botiquin, kit derrames, documentos, vehiculo, tamizajes, sensibilización peligros y riesgos"
  },
  {
    "CLIENTE - LUGAR VISITA": "Chemilab",
    "CIUDAD": "Medellín",
    "FECHA": 46043,
    "GESTOR LOGISTICO": "Sara Pasos",
    "EJECUTADA": "SI",
    "ACTIVIDAD A REALIZAR POR EL GESTOR": "Se cuenta con acompañamiento del gestor",
    "SE GENERA ACOMPAÑAMIENTO ÁREA SGI": "Daniela Vergara",
    "AREA": "SST",
    "ESTADO DE VISITA": "Ejecutada",
    "CANT. PERSONAL IMPACTADO": 5,
    "TEMAS ABORDADOS": "Momentos de seguridad, manejo integreal de residuos, emisiones CO2, Inspecciones, tamizajes"
  },
  {
    "CLIENTE - LUGAR VISITA": "EPM - Centro Tecnico",
    "CIUDAD": "Medellín",
    "FECHA": 46048,
    "GESTOR LOGISTICO": "Carlos Franco",
    "EJECUTADA": "SI",
    "ACTIVIDAD A REALIZAR POR EL GESTOR": "Sin acompañamiento del gestor",
    "SE GENERA ACOMPAÑAMIENTO ÁREA SGI": "Farley Velandia",
    "AREA": "SST",
    "ESTADO DE VISITA": "Ejecutada",
    "CANT. PERSONAL IMPACTADO": 10,
    "TEMAS ABORDADOS": "Sensibilización sobre peligros y riesgos, tamizajes de embriaguez"
  },
  {
    "CLIENTE - LUGAR VISITA": "EPM - Hidroituango",
    "CIUDAD": "Ituango",
    "FECHA": 46049,
    "GESTOR LOGISTICO": "Carlos Franco",
    "EJECUTADA": "SI",
    "ACTIVIDAD A REALIZAR POR EL GESTOR": "Sin acompañamiento del gestor",
    "SE GENERA ACOMPAÑAMIENTO ÁREA SGI": "Dayana Restrepo",
    "AREA": "SST",
    "ESTADO DE VISITA": "Ejecutada",
    "CANT. PERSONAL IMPACTADO": 17,
    "TEMAS ABORDADOS": "Capacitación Tremo"
  },
  {
    "CLIENTE - LUGAR VISITA": "EPM - Hidroituango",
    "CIUDAD": "Ituango",
    "FECHA": 46050,
    "GESTOR LOGISTICO": "Carlos Franco",
    "EJECUTADA": "SI",
    "ACTIVIDAD A REALIZAR POR EL GESTOR": "Sin acompañamiento del gestor",
    "SE GENERA ACOMPAÑAMIENTO ÁREA SGI": "Dayana Restrepo",
    "AREA": "SST",
    "ESTADO DE VISITA": "Ejecutada",
    "CANT. PERSONAL IMPACTADO": 21,
    "TEMAS ABORDADOS": "Capacitación Tremo"
  },
  {
    "CLIENTE - LUGAR VISITA": "EPM - Hidroituango",
    "CIUDAD": "Ituango",
    "FECHA": 46051,
    "GESTOR LOGISTICO": "Carlos Franco",
    "EJECUTADA": "SI",
    "ACTIVIDAD A REALIZAR POR EL GESTOR": "Sin acompañamiento del gestor",
    "SE GENERA ACOMPAÑAMIENTO ÁREA SGI": "Dayana Restrepo",
    "AREA": "SST",
    "ESTADO DE VISITA": "Ejecutada",
    "CANT. PERSONAL IMPACTADO": 15,
    "TEMAS ABORDADOS": "Capacitación Tremo"
  },
  {
    "CLIENTE - LUGAR VISITA": "EPM - Hidroituango",
    "CIUDAD": "Ituango",
    "FECHA": 46052,
    "GESTOR LOGISTICO": "Carlos Franco",
    "EJECUTADA": "SI",
    "ACTIVIDAD A REALIZAR POR EL GESTOR": "Sin acompañamiento del gestor",
    "SE GENERA ACOMPAÑAMIENTO ÁREA SGI": "Dayana Restrepo",
    "AREA": "SST",
    "ESTADO DE VISITA": "Ejecutada",
    "CANT. PERSONAL IMPACTADO": 19,
    "TEMAS ABORDADOS": "Tamizajes Embriaguez"
  },
  {
    "CLIENTE - LUGAR VISITA": "Chemilab",
    "CIUDAD": "Medellín",
    "FECHA": 46053,
    "GESTOR LOGISTICO": "Sara Pasos",
    "EJECUTADA": "SI",
    "ACTIVIDAD A REALIZAR POR EL GESTOR": "Se cuenta con acompañamiento del gestor",
    "SE GENERA ACOMPAÑAMIENTO ÁREA SGI": "Daniela Vergara",
    "AREA": "SST",
    "ESTADO DE VISITA": "Ejecutada",
    "CANT. PERSONAL IMPACTADO": 4,
    "TEMAS ABORDADOS": "Momentos de seguridad, manejo defensivo, reporte de novedades, lecciones aprendidas, identificación de peligros y riesgos"
  },
  {
    "CLIENTE - LUGAR VISITA": "ISAGEN - San Carlos",
    "CIUDAD": "San Carlos",
    "FECHA": 46055,
    "GESTOR LOGISTICO": "Diana Alvarez",
    "EJECUTADA": "SI",
    "ACTIVIDAD A REALIZAR POR EL GESTOR": "Se cuenta con acompañamiento del gestor",
    "SE GENERA ACOMPAÑAMIENTO ÁREA SGI": "Daniela Vergara",
    "AREA": "SST",
    "ESTADO DE VISITA": "Ejecutada",
    "CANT. PERSONAL IMPACTADO": 4,
    "TEMAS ABORDADOS": "Protocolo conductores de carga, Pausas activas, Programación horarios, rotacaion conductores, Indentificacion condiciones viales "
  },
  {
    "CLIENTE - LUGAR VISITA": "ISAGEN - San Carlos",
    "CIUDAD": "San Carlos",
    "FECHA": 46056,
    "GESTOR LOGISTICO": "Diana Alvarez",
    "EJECUTADA": "SI",
    "ACTIVIDAD A REALIZAR POR EL GESTOR": "Se cuenta con acompañamiento del gestor",
    "SE GENERA ACOMPAÑAMIENTO ÁREA SGI": "Daniela Vergara",
    "AREA": "SST",
    "ESTADO DE VISITA": "Ejecutada",
    "CANT. PERSONAL IMPACTADO": 15,
    "TEMAS ABORDADOS": "Acompañamiento pausa activa integral psicosocial Andrea Buritica, Estimulacion mental y cuidado de la salud mental"
  },
  {
    "CLIENTE - LUGAR VISITA": "ISAGEN - San Carlos",
    "CIUDAD": "San Carlos",
    "FECHA": 46056,
    "GESTOR LOGISTICO": "Diana Alvarez",
    "EJECUTADA": "SI",
    "ACTIVIDAD A REALIZAR POR EL GESTOR": "Se cuenta con acompañamiento del gestor",
    "SE GENERA ACOMPAÑAMIENTO ÁREA SGI": "Daniela Vergara",
    "AREA": "SST",
    "ESTADO DE VISITA": "Ejecutada",
    "CANT. PERSONAL IMPACTADO": 13,
    "TEMAS ABORDADOS": "Reporte de accidentes, inspecciones de vehículos, programas PESV, tamizajes"
  },
  {
    "CLIENTE - LUGAR VISITA": "EPM - Edificio inteligente",
    "CIUDAD": "Medellín",
    "FECHA": 46056,
    "GESTOR LOGISTICO": "Carlos Franco",
    "EJECUTADA": "SI",
    "ACTIVIDAD A REALIZAR POR EL GESTOR": "Sin acompañamiento del gestor",
    "SE GENERA ACOMPAÑAMIENTO ÁREA SGI": "Dalila Anaya",
    "AREA": "SST",
    "ESTADO DE VISITA": "Ejecutada",
    "CANT. PERSONAL IMPACTADO": 6,
    "TEMAS ABORDADOS": "prevención del consumo de sustancias psicoactivas, tamizajes, pausas activas, ergonomioa en conductores acompañamiento Paola Galvis"
  },
  {
    "CLIENTE - LUGAR VISITA": "ISAGEN - Jaguas / Calderas",
    "CIUDAD": "San Rafael",
    "FECHA": 46057,
    "GESTOR LOGISTICO": "Diana Alvarez",
    "EJECUTADA": "SI",
    "ACTIVIDAD A REALIZAR POR EL GESTOR": "Se cuenta con acompañamiento del gestor",
    "SE GENERA ACOMPAÑAMIENTO ÁREA SGI": "Daniela Vergara",
    "AREA": "SST",
    "ESTADO DE VISITA": "Ejecutada",
    "CANT. PERSONAL IMPACTADO": 3,
    "TEMAS ABORDADOS": "Acompañamiento pausa activa integral psicosocial Andrea Buritica, Estimulacion mental y cuidado de la salud mental"
  },
  {
    "CLIENTE - LUGAR VISITA": "ISAGEN - Jaguas / Calderas",
    "CIUDAD": "San Rafael",
    "FECHA": 46057,
    "GESTOR LOGISTICO": "Diana Alvarez",
    "EJECUTADA": "SI",
    "ACTIVIDAD A REALIZAR POR EL GESTOR": "Se cuenta con acompañamiento del gestor",
    "SE GENERA ACOMPAÑAMIENTO ÁREA SGI": "Daniela Vergara",
    "AREA": "SST",
    "ESTADO DE VISITA": "Ejecutada",
    "CANT. PERSONAL IMPACTADO": 4,
    "TEMAS ABORDADOS": "Reporte de accidentes, inspecciones de vehículos, programas PESV, tamizajes"
  },
  {
    "CLIENTE - LUGAR VISITA": "Telemedellin ",
    "CIUDAD": "Medellín",
    "FECHA": 46059,
    "GESTOR LOGISTICO": "Julieth Higuita",
    "EJECUTADA": "SI",
    "ACTIVIDAD A REALIZAR POR EL GESTOR": "Se cuenta con acompañamiento del gestor",
    "SE GENERA ACOMPAÑAMIENTO ÁREA SGI": "Dayana Restrepo",
    "AREA": "SST",
    "ESTADO DE VISITA": "Ejecutada",
    "CANT. PERSONAL IMPACTADO": 6,
    "TEMAS ABORDADOS": "Inspección vehiculos, Tamizajes embriaguez, elementos de protección"
  },
  {
    "CLIENTE - LUGAR VISITA": "EPM - Centro Tecnico",
    "CIUDAD": "Medellín",
    "FECHA": 46062,
    "GESTOR LOGISTICO": "Carlos Franco",
    "EJECUTADA": "SI",
    "ACTIVIDAD A REALIZAR POR EL GESTOR": "Se cuenta con acompañamiento del gestor",
    "SE GENERA ACOMPAÑAMIENTO ÁREA SGI": "Dayana Restrepo ",
    "AREA": "SST",
    "ESTADO DE VISITA": "Ejecutada",
    "CANT. PERSONAL IMPACTADO": 7,
    "TEMAS ABORDADOS": "Prevención consumo alochol y sustancias - Tamizajes Embriaguez"
  },
  {
    "CLIENTE - LUGAR VISITA": "CAH - Niñez (San Javier)",
    "CIUDAD": "Medellín",
    "FECHA": 46064,
    "GESTOR LOGISTICO": "Dayhana Sossa",
    "EJECUTADA": "SI",
    "ACTIVIDAD A REALIZAR POR EL GESTOR": "Se cuenta con acompañamiento del gestor",
    "SE GENERA ACOMPAÑAMIENTO ÁREA SGI": "Dalila Anaya",
    "AREA": "SST",
    "ESTADO DE VISITA": "Ejecutada",
    "CANT. PERSONAL IMPACTADO": 5,
    "TEMAS ABORDADOS": "Prevención consumo alochol y sustancias - Tamizajes Embriaguez - Reporte de condiciones inseguras - Reporte de AT"
  },
  {
    "CLIENTE - LUGAR VISITA": "Jardin Botánico",
    "CIUDAD": "Medellín",
    "FECHA": 46064,
    "GESTOR LOGISTICO": "Yesid Carvajal",
    "EJECUTADA": "SI",
    "ACTIVIDAD A REALIZAR POR EL GESTOR": "Se cuenta con acompañamiento del gestor",
    "SE GENERA ACOMPAÑAMIENTO ÁREA SGI": "Dayana Restrepo ",
    "AREA": "SST",
    "ESTADO DE VISITA": "Ejecutada",
    "CANT. PERSONAL IMPACTADO": 4,
    "TEMAS ABORDADOS": "Prevención consumo alochol y sustancias - Tamizajes Embriaguez"
  },
  {
    "CLIENTE - LUGAR VISITA": "Jardin Botánico",
    "CIUDAD": "Medellín",
    "FECHA": 46069,
    "GESTOR LOGISTICO": "Yesid Carvajal",
    "EJECUTADA": "NO",
    "ACTIVIDAD A REALIZAR POR EL GESTOR": "Sin acompañamiento del gestor",
    "SE GENERA ACOMPAÑAMIENTO ÁREA SGI": "Dayana restrepo",
    "AREA": "SST",
    "ESTADO DE VISITA": "Sin Ejecutar",
    "CANT. PERSONAL IMPACTADO": 0,
    "TEMAS ABORDADOS": "No se coordina con gestor "
  },
  {
    "CLIENTE - LUGAR VISITA": "Medicarte",
    "CIUDAD": "Medellín",
    "FECHA": 46070,
    "GESTOR LOGISTICO": "Sara Pasos",
    "EJECUTADA": "SI",
    "ACTIVIDAD A REALIZAR POR EL GESTOR": "Se cuenta con acompañamiento del gestor",
    "SE GENERA ACOMPAÑAMIENTO ÁREA SGI": "Farley Velandia",
    "AREA": "SST",
    "ESTADO DE VISITA": "Ejecutada",
    "CANT. PERSONAL IMPACTADO": 4,
    "TEMAS ABORDADOS": "Identificación peligros y riesgos, Conducción a la defensiva, fortalecimiento seguridad vial, normas y señales de transito"
  },
  {
    "CLIENTE - LUGAR VISITA": "Chemilab",
    "CIUDAD": "Medellín",
    "FECHA": 46070,
    "GESTOR LOGISTICO": "Sara Pasos",
    "EJECUTADA": "SI",
    "ACTIVIDAD A REALIZAR POR EL GESTOR": "Se cuenta con acompañamiento del gestor",
    "SE GENERA ACOMPAÑAMIENTO ÁREA SGI": "Farley Velandia",
    "AREA": "SST",
    "ESTADO DE VISITA": "Ejecutada",
    "CANT. PERSONAL IMPACTADO": 4,
    "TEMAS ABORDADOS": "Identificación peligros y riesgos, Conducción a la defensiva, fortalecimiento seguridad vial, normas y señales de transito"
  },
  {
    "CLIENTE - LUGAR VISITA": "EPM - Hidroituango",
    "CIUDAD": "Ituango",
    "FECHA": 46071,
    "GESTOR LOGISTICO": "Carlos Franco",
    "EJECUTADA": "NO",
    "ACTIVIDAD A REALIZAR POR EL GESTOR": "Sin acompañamiento del gestor",
    "SE GENERA ACOMPAÑAMIENTO ÁREA SGI": "Dayana Restrepo",
    "AREA": "SST",
    "ESTADO DE VISITA": "Sin Ejecutar",
    "CANT. PERSONAL IMPACTADO": 0,
    "TEMAS ABORDADOS": "No se coordina con gestor "
  },
  {
    "CLIENTE - LUGAR VISITA": "EPM - Hidroituango",
    "CIUDAD": "Ituango",
    "FECHA": 46072,
    "GESTOR LOGISTICO": "Carlos Franco",
    "EJECUTADA": "NO",
    "ACTIVIDAD A REALIZAR POR EL GESTOR": "Sin acompañamiento del gestor",
    "SE GENERA ACOMPAÑAMIENTO ÁREA SGI": "Dayana Restrepo",
    "AREA": "SST",
    "ESTADO DE VISITA": "Sin Ejecutar",
    "CANT. PERSONAL IMPACTADO": 0,
    "TEMAS ABORDADOS": "No se coordina con gestor "
  },
  {
    "CLIENTE - LUGAR VISITA": "EPM - Hidroituango",
    "CIUDAD": "Ituango",
    "FECHA": 46073,
    "GESTOR LOGISTICO": "Carlos Franco",
    "EJECUTADA": "NO",
    "ACTIVIDAD A REALIZAR POR EL GESTOR": "Sin acompañamiento del gestor",
    "SE GENERA ACOMPAÑAMIENTO ÁREA SGI": "Dayana Restrepo",
    "AREA": "SST",
    "ESTADO DE VISITA": "Sin Ejecutar",
    "CANT. PERSONAL IMPACTADO": 0,
    "TEMAS ABORDADOS": "No se coordina con gestor "
  },
  {
    "CLIENTE - LUGAR VISITA": "CAH - Niñez (San Javier)",
    "CIUDAD": "Medellín",
    "FECHA": 46076,
    "GESTOR LOGISTICO": "Dayhana Sossa",
    "EJECUTADA": "SI",
    "ACTIVIDAD A REALIZAR POR EL GESTOR": "Se cuenta con acompañamiento del gestor",
    "SE GENERA ACOMPAÑAMIENTO ÁREA SGI": "Dalila Anaya",
    "AREA": "SST",
    "ESTADO DE VISITA": "Ejecutada",
    "CANT. PERSONAL IMPACTADO": 14,
    "TEMAS ABORDADOS": "Socialización Riesgo público"
  },
  {
    "CLIENTE - LUGAR VISITA": "ISAGEN - PCH",
    "CIUDAD": "Cocorna",
    "FECHA": 46076,
    "GESTOR LOGISTICO": "Lizzeth Arbelaez",
    "EJECUTADA": "SI",
    "ACTIVIDAD A REALIZAR POR EL GESTOR": "Se cuenta con acompañamiento del gestor",
    "SE GENERA ACOMPAÑAMIENTO ÁREA SGI": "Daniela Vergara",
    "AREA": "SST",
    "ESTADO DE VISITA": "Ejecutada",
    "CANT. PERSONAL IMPACTADO": 6,
    "TEMAS ABORDADOS": "Programa de seguridad vial, Identificación peligros y riesgos, Manejo defensivo, Inspecciones, tamizajes"
  },
  {
    "CLIENTE - LUGAR VISITA": "CAH -Niñez",
    "CIUDAD": "Medellín",
    "FECHA": 46077,
    "GESTOR LOGISTICO": "Dayhana Sossa",
    "EJECUTADA": "SI",
    "ACTIVIDAD A REALIZAR POR EL GESTOR": "Se cuenta con acompañamiento del gestor",
    "SE GENERA ACOMPAÑAMIENTO ÁREA SGI": "Farley Velandia",
    "AREA": "SST",
    "ESTADO DE VISITA": "Ejecutada",
    "CANT. PERSONAL IMPACTADO": 19,
    "TEMAS ABORDADOS": "Lineas de emergencia, prevención de los riesgos en los servicios "
  },
  {
    "CLIENTE - LUGAR VISITA": "Jardin Botánico",
    "CIUDAD": "Medellín",
    "FECHA": 46083,
    "GESTOR LOGISTICO": "Yesid Carvajal",
    "EJECUTADA": "NO",
    "ACTIVIDAD A REALIZAR POR EL GESTOR": "Sin acompañamiento del gestor",
    "SE GENERA ACOMPAÑAMIENTO ÁREA SGI": "Dayana Restrepo",
    "AREA": "SST",
    "ESTADO DE VISITA": "Sin Ejecutar",
    "CANT. PERSONAL IMPACTADO": 0,
    "TEMAS ABORDADOS": "No se coordina con gestor "
  },
  {
    "CLIENTE - LUGAR VISITA": "EPM - Edificio inteligente",
    "CIUDAD": "Medellín",
    "FECHA": 46084,
    "GESTOR LOGISTICO": "Carlos Franco",
    "EJECUTADA": "NO",
    "ACTIVIDAD A REALIZAR POR EL GESTOR": "Sin acompañamiento del gestor",
    "SE GENERA ACOMPAÑAMIENTO ÁREA SGI": "Dayana Restrepo",
    "AREA": "SST",
    "ESTADO DE VISITA": "Sin Ejecutar",
    "CANT. PERSONAL IMPACTADO": 0,
    "TEMAS ABORDADOS": "No se coordina con gestor "
  },
  {
    "CLIENTE - LUGAR VISITA": "Medicarte",
    "CIUDAD": "Medellín",
    "FECHA": 46084,
    "GESTOR LOGISTICO": "Sara Pasos",
    "EJECUTADA": "NO",
    "ACTIVIDAD A REALIZAR POR EL GESTOR": "No se coordina con gestor ",
    "SE GENERA ACOMPAÑAMIENTO ÁREA SGI": "Farley Velandia",
    "AREA": "SST",
    "ESTADO DE VISITA": "Sin Ejecutar",
    "CANT. PERSONAL IMPACTADO": 0,
    "TEMAS ABORDADOS": "No se coordina con gestor "
  },
  {
    "CLIENTE - LUGAR VISITA": "EPM - Centro Tecnico",
    "CIUDAD": "Medellín",
    "FECHA": 46090,
    "GESTOR LOGISTICO": "Carlos Franco",
    "EJECUTADA": "SI",
    "ACTIVIDAD A REALIZAR POR EL GESTOR": "Sin acompañamiento del gestor",
    "SE GENERA ACOMPAÑAMIENTO ÁREA SGI": "Dayana Restrepo",
    "AREA": "SST",
    "ESTADO DE VISITA": "Ejecutada",
    "CANT. PERSONAL IMPACTADO": 17,
    "TEMAS ABORDADOS": "Prevención consumo alochol y sustancias - Tamizajes Embriaguez - Momentos de seguridad - PESV"
  },
  {
    "CLIENTE - LUGAR VISITA": "CAH - 123 Social",
    "CIUDAD": "Medellín",
    "FECHA": 46090,
    "GESTOR LOGISTICO": "Dayhana Sossa",
    "EJECUTADA": "SI",
    "ACTIVIDAD A REALIZAR POR EL GESTOR": "Se cuenta con acompañamiento del gestor",
    "SE GENERA ACOMPAÑAMIENTO ÁREA SGI": "Dalila Anaya",
    "AREA": "SST",
    "ESTADO DE VISITA": "Ejecutada",
    "CANT. PERSONAL IMPACTADO": 21,
    "TEMAS ABORDADOS": "Reporte de accidentes, inspecciones de vehículos, programas PESV, tamizajes - Documentación obligatoria"
  },
  {
    "CLIENTE - LUGAR VISITA": "Jardin Botánico",
    "CIUDAD": "Medellín",
    "FECHA": 46092,
    "GESTOR LOGISTICO": "Yesid Carvajal",
    "EJECUTADA": "SI",
    "ACTIVIDAD A REALIZAR POR EL GESTOR": "Se cuenta con acompañamiento del gestor",
    "SE GENERA ACOMPAÑAMIENTO ÁREA SGI": "Dayana Restrepo",
    "AREA": "SST",
    "ESTADO DE VISITA": "Ejecutada",
    "CANT. PERSONAL IMPACTADO": 11,
    "TEMAS ABORDADOS": "Prevención consumo alochol y sustancias - Tamizajes Embriaguez - Momentos de seguridad - PESV"
  },
  {
    "CLIENTE - LUGAR VISITA": "Sura Industruales",
    "CIUDAD": "Medellín",
    "FECHA": 46094,
    "GESTOR LOGISTICO": "Equipo salud ",
    "EJECUTADA": "SI",
    "ACTIVIDAD A REALIZAR POR EL GESTOR": "Se cuenta con acompañamiento del gestor",
    "SE GENERA ACOMPAÑAMIENTO ÁREA SGI": "Farley Velandia",
    "AREA": "SST",
    "ESTADO DE VISITA": "Ejecutada",
    "CANT. PERSONAL IMPACTADO": 38,
    "TEMAS ABORDADOS": "Tamizajes Embriaguez - seguridad vial - reporte de accidentes"
  },
  {
    "CLIENTE - LUGAR VISITA": "EPM - Edificio inteligente",
    "CIUDAD": "Medellín",
    "FECHA": 46097,
    "GESTOR LOGISTICO": "Carlos Franco",
    "EJECUTADA": "SI",
    "ACTIVIDAD A REALIZAR POR EL GESTOR": "Sin acompañamiento del gestor",
    "SE GENERA ACOMPAÑAMIENTO ÁREA SGI": "Dayana Restrepo",
    "AREA": "SST",
    "ESTADO DE VISITA": "Ejecutada",
    "CANT. PERSONAL IMPACTADO": 11,
    "TEMAS ABORDADOS": "Prevención consumo alochol y sustancias - Tamizajes Embriaguez - Momentos de seguridad - PESV"
  },
  {
    "CLIENTE - LUGAR VISITA": "Jardin Botánico",
    "CIUDAD": "Medellín",
    "FECHA": 46097,
    "GESTOR LOGISTICO": "Yesid Carvajal",
    "EJECUTADA": "SI",
    "ACTIVIDAD A REALIZAR POR EL GESTOR": "Se cuenta con acompañamiento del gestor",
    "SE GENERA ACOMPAÑAMIENTO ÁREA SGI": "Farley Velandia",
    "AREA": "SST",
    "ESTADO DE VISITA": "Ejecutada",
    "CANT. PERSONAL IMPACTADO": 9,
    "TEMAS ABORDADOS": "Prevención consumo alochol y sustancias - Tamizajes Embriaguez - Momentos de seguridad - PESV"
  },
  {
    "CLIENTE - LUGAR VISITA": "CAH - Niñez (San Javier)",
    "CIUDAD": "Medellín",
    "FECHA": 46098,
    "GESTOR LOGISTICO": "Dayhana Sossa",
    "EJECUTADA": "SI",
    "ACTIVIDAD A REALIZAR POR EL GESTOR": "Se cuenta con acompañamiento del gestor",
    "SE GENERA ACOMPAÑAMIENTO ÁREA SGI": "Dalila Anaya ",
    "AREA": "SST",
    "ESTADO DE VISITA": "Ejecutada",
    "CANT. PERSONAL IMPACTADO": 3,
    "TEMAS ABORDADOS": "Tamizajes, prevención osteomuscular- Pausas activas"
  },
  {
    "CLIENTE - LUGAR VISITA": "EPM - Porce III - Los Cedros - Guadalupe",
    "CIUDAD": "Guadalupe",
    "FECHA": 46098,
    "GESTOR LOGISTICO": "Carlos Franco",
    "EJECUTADA": "NO",
    "ACTIVIDAD A REALIZAR POR EL GESTOR": "Sin acompañamiento del gestor",
    "SE GENERA ACOMPAÑAMIENTO ÁREA SGI": "Daniela Vergara",
    "AREA": "SST",
    "ESTADO DE VISITA": "Sin Ejecutar",
    "CANT. PERSONAL IMPACTADO": 0,
    "TEMAS ABORDADOS": "No se coordina con gestor "
  },
  {
    "CLIENTE - LUGAR VISITA": "EPM - Porce III - Los Cedros - Guadalupe",
    "CIUDAD": "Guadalupe",
    "FECHA": 46098,
    "GESTOR LOGISTICO": "Carlos Franco",
    "EJECUTADA": "NO",
    "ACTIVIDAD A REALIZAR POR EL GESTOR": "Sin acompañamiento del gestor",
    "SE GENERA ACOMPAÑAMIENTO ÁREA SGI": "Daniela Vergara",
    "AREA": "SST",
    "ESTADO DE VISITA": "Sin Ejecutar",
    "CANT. PERSONAL IMPACTADO": 0,
    "TEMAS ABORDADOS": "No se coordina con gestor "
  },
  {
    "CLIENTE - LUGAR VISITA": "Telemedellin ",
    "CIUDAD": "Medellín",
    "FECHA": 46101,
    "GESTOR LOGISTICO": "Julieth Higuita",
    "EJECUTADA": "SI",
    "ACTIVIDAD A REALIZAR POR EL GESTOR": "Se cuenta con acompañamiento del gestor",
    "SE GENERA ACOMPAÑAMIENTO ÁREA SGI": "Dayana Restrepo",
    "AREA": "SST",
    "ESTADO DE VISITA": "Ejecutada",
    "CANT. PERSONAL IMPACTADO": 8,
    "TEMAS ABORDADOS": "Prevención consumo alochol y sustancias - Tamizajes Embriaguez - Momentos de seguridad - PESV"
  },
  {
    "CLIENTE - LUGAR VISITA": "EPM - Centro Tecnico",
    "CIUDAD": "Medellín",
    "FECHA": 46105,
    "GESTOR LOGISTICO": "Carlos Franco",
    "EJECUTADA": "SI",
    "ACTIVIDAD A REALIZAR POR EL GESTOR": "Sin acompañamiento del gestor",
    "SE GENERA ACOMPAÑAMIENTO ÁREA SGI": "Farley Velandia",
    "AREA": "SST",
    "ESTADO DE VISITA": "Ejecutada",
    "CANT. PERSONAL IMPACTADO": 11,
    "TEMAS ABORDADOS": "Prevención consumo alochol y sustancias - Tamizajes Embriaguez - Momentos de seguridad - PESV"
  },
  {
    "CLIENTE - LUGAR VISITA": "CAH - Niñez (San Javier)",
    "CIUDAD": "Medellín",
    "FECHA": 46105,
    "GESTOR LOGISTICO": "Dayhana Sossa",
    "EJECUTADA": "NO",
    "ACTIVIDAD A REALIZAR POR EL GESTOR": "Sin acompañamiento del gestor",
    "SE GENERA ACOMPAÑAMIENTO ÁREA SGI": "Dayana Restrepo",
    "AREA": "SST",
    "ESTADO DE VISITA": "Sin Ejecutar",
    "CANT. PERSONAL IMPACTADO": 0,
    "TEMAS ABORDADOS": "No se coordina con gestor "
  },
  {
    "CLIENTE - LUGAR VISITA": "Jardin Botánico",
    "CIUDAD": "Medellín",
    "FECHA": 46106,
    "GESTOR LOGISTICO": "Yesid Carvajal",
    "EJECUTADA": "SI",
    "ACTIVIDAD A REALIZAR POR EL GESTOR": "Se cuenta con acompañamiento del gestor",
    "SE GENERA ACOMPAÑAMIENTO ÁREA SGI": "Dalila Anaya ",
    "AREA": "SST",
    "ESTADO DE VISITA": "Ejecutada",
    "CANT. PERSONAL IMPACTADO": 17,
    "TEMAS ABORDADOS": "Prevención consumo alochol y sustancias - Tamizajes Embriaguez - Momentos de seguridad - PESV - lecciones aprendidas - Reportes accidentes - Identificación peligros y riesgos"
  },
  {
    "CLIENTE - LUGAR VISITA": "Sura Industruales",
    "CIUDAD": "Medellín",
    "FECHA": 46111,
    "GESTOR LOGISTICO": "Equipo salud ",
    "EJECUTADA": "NO",
    "ACTIVIDAD A REALIZAR POR EL GESTOR": "Sin acompañamiento del gestor",
    "SE GENERA ACOMPAÑAMIENTO ÁREA SGI": "Dalila Anaya",
    "AREA": "SST",
    "ESTADO DE VISITA": "Sin Ejecutar",
    "CANT. PERSONAL IMPACTADO": 0,
    "TEMAS ABORDADOS": "No se coordina con gestor "
  },
  {
    "CLIENTE - LUGAR VISITA": "Chemilab",
    "CIUDAD": "Medellín",
    "FECHA": 46112,
    "GESTOR LOGISTICO": "Edwin Aguirre",
    "EJECUTADA": "SI",
    "ACTIVIDAD A REALIZAR POR EL GESTOR": "Se cuenta con acompañamiento del gestor",
    "SE GENERA ACOMPAÑAMIENTO ÁREA SGI": "Dalila Anaya ",
    "AREA": "SST",
    "ESTADO DE VISITA": "Ejecutada",
    "CANT. PERSONAL IMPACTADO": 2,
    "TEMAS ABORDADOS": "Prevención consumo alochol y sustancias - Tamizajes Embriaguez - Momentos de seguridad - PESV - lecciones aprendidas - Reportes accidentes - Identificación peligros y riesgos"
  },
  {
    "CLIENTE - LUGAR VISITA": "CAH - Niñez (San Javier)",
    "CIUDAD": "Medellín",
    "FECHA": 46120,
    "GESTOR LOGISTICO": "Dayhana Sossa",
    "EJECUTADA": "SI",
    "ACTIVIDAD A REALIZAR POR EL GESTOR": "Se cuenta con acompañamiento del gestor",
    "SE GENERA ACOMPAÑAMIENTO ÁREA SGI": "Dalila Anaya",
    "AREA": "SST",
    "ESTADO DE VISITA": "Ejecutada ",
    "CANT. PERSONAL IMPACTADO": 9,
    "TEMAS ABORDADOS": "Prevención consumo alochol y sustancias - Tamizajes Embriaguez - Momentos de seguridad - PESV - lecciones aprendidas - Reportes accidentes - Identificación peligros y riesgos / Acompañamiento psicosocial Andrea buritica y Osteomuscular Paola Galvis"
  },
  {
    "CLIENTE - LUGAR VISITA": "Sura Industruales",
    "CIUDAD": "Medellín",
    "FECHA": 46120,
    "GESTOR LOGISTICO": "Equipo salud ",
    "EJECUTADA": "SI",
    "ACTIVIDAD A REALIZAR POR EL GESTOR": "Se cuenta con acompañamiento del gestor",
    "SE GENERA ACOMPAÑAMIENTO ÁREA SGI": "Dalila Anaya",
    "AREA": "SST",
    "ESTADO DE VISITA": "Ejecutada ",
    "CANT. PERSONAL IMPACTADO": 11,
    "TEMAS ABORDADOS": "Prevención consumo alochol y sustancias - Tamizajes Embriaguez - Momentos de seguridad - PESV - lecciones aprendidas - Reportes accidentes - Identificación peligros y riesgos / Acompañamiento psicosocial Andrea buritica y Osteomuscular Paola Galvis"
  },
  {
    "CLIENTE - LUGAR VISITA": "CAH - Agencia Mujer ",
    "CIUDAD": "Medellín",
    "FECHA": 46121,
    "GESTOR LOGISTICO": "Dayhana Sossa",
    "EJECUTADA": "SI",
    "ACTIVIDAD A REALIZAR POR EL GESTOR": "Se cuenta con acompañamiento del gestor",
    "SE GENERA ACOMPAÑAMIENTO ÁREA SGI": "Dalila Anaya",
    "AREA": "SST",
    "ESTADO DE VISITA": "Ejecutada ",
    "CANT. PERSONAL IMPACTADO": 9,
    "TEMAS ABORDADOS": "Prevención consumo alochol y sustancias - Tamizajes Embriaguez - Momentos de seguridad - PESV - lecciones aprendidas - Reportes accidentes - Identificación peligros y riesgos / Acompañamiento psicosocial Andrea buritica"
  },
  {
    "CLIENTE - LUGAR VISITA": "ISAGEN - San Carlos",
    "CIUDAD": "San Carlos",
    "FECHA": 46126,
    "GESTOR LOGISTICO": "Diana Alvarez",
    "EJECUTADA": "SI",
    "ACTIVIDAD A REALIZAR POR EL GESTOR": "Se cuenta con acompañamiento del gestor",
    "SE GENERA ACOMPAÑAMIENTO ÁREA SGI": "Angy Arzuza",
    "AREA": "SST",
    "ESTADO DE VISITA": "Ejecutada ",
    "CANT. PERSONAL IMPACTADO": 10,
    "TEMAS ABORDADOS": "Capacitación manejo camión grua - Acopañamiento proveedor de la ARL"
  },
  {
    "CLIENTE - LUGAR VISITA": "ISAGEN - San Carlos",
    "CIUDAD": "San Carlos",
    "FECHA": 46127,
    "GESTOR LOGISTICO": "Diana Alvarez",
    "EJECUTADA": "SI",
    "ACTIVIDAD A REALIZAR POR EL GESTOR": "Se cuenta con acompañamiento del gestor",
    "SE GENERA ACOMPAÑAMIENTO ÁREA SGI": "Angy Arzuza",
    "AREA": "SST",
    "ESTADO DE VISITA": "Ejecutada ",
    "CANT. PERSONAL IMPACTADO": 10,
    "TEMAS ABORDADOS": "Capacitación manejo camión grua - Acopañamiento proveedor de la ARL"
  },
  {
    "CLIENTE - LUGAR VISITA": "Jardin Botánico",
    "CIUDAD": "Medellín",
    "FECHA": 46127,
    "GESTOR LOGISTICO": "Yesid Carvajal",
    "EJECUTADA": "NO",
    "ACTIVIDAD A REALIZAR POR EL GESTOR": "Sin acompañamiento del gestor",
    "SE GENERA ACOMPAÑAMIENTO ÁREA SGI": "Dayana Restrepo ",
    "AREA": "SST",
    "ESTADO DE VISITA": "SIN EJECUTAR",
    "CANT. PERSONAL IMPACTADO": 0,
    "TEMAS ABORDADOS": "No se coordina con gestor "
  },
  {
    "CLIENTE - LUGAR VISITA": "Chemilab",
    "CIUDAD": "Medellín",
    "FECHA": 46128,
    "GESTOR LOGISTICO": "Edwin Aguirre",
    "EJECUTADA": "NO",
    "ACTIVIDAD A REALIZAR POR EL GESTOR": "Sin acompañamiento del gestor",
    "SE GENERA ACOMPAÑAMIENTO ÁREA SGI": "Dayana Restrepo ",
    "AREA": "SST",
    "ESTADO DE VISITA": "Sin Ejecutar",
    "CANT. PERSONAL IMPACTADO": 0,
    "TEMAS ABORDADOS": "No se coordina con gestor "
  },
  {
    "CLIENTE - LUGAR VISITA": "CAH - Niñez (San Javier)",
    "CIUDAD": "Medellín",
    "FECHA": 46132,
    "GESTOR LOGISTICO": "Dayhana Sossa",
    "EJECUTADA": "NO",
    "ACTIVIDAD A REALIZAR POR EL GESTOR": "Sin acompañamiento del gestor",
    "SE GENERA ACOMPAÑAMIENTO ÁREA SGI": "Dalila Anaya",
    "AREA": "SST",
    "ESTADO DE VISITA": "Sin Ejecutar",
    "CANT. PERSONAL IMPACTADO": 0,
    "TEMAS ABORDADOS": "No se coordina con gestor "
  },
  {
    "CLIENTE - LUGAR VISITA": "Sura Industruales",
    "CIUDAD": "Medellín",
    "FECHA": 46132,
    "GESTOR LOGISTICO": "Equipo salud ",
    "EJECUTADA": "NO",
    "ACTIVIDAD A REALIZAR POR EL GESTOR": "Sin acompañamiento del gestor",
    "SE GENERA ACOMPAÑAMIENTO ÁREA SGI": "Dayana Restrepo ",
    "AREA": "SST",
    "ESTADO DE VISITA": "Sin Ejecutar",
    "CANT. PERSONAL IMPACTADO": 0,
    "TEMAS ABORDADOS": "No se coordina con gestor "
  },
  {
    "CLIENTE - LUGAR VISITA": "Telemedellin ",
    "CIUDAD": "Medellín",
    "FECHA": 46136,
    "GESTOR LOGISTICO": "Julieth Higuita",
    "EJECUTADA": "SI",
    "ACTIVIDAD A REALIZAR POR EL GESTOR": "Se cuenta con acompañamiento del gestor",
    "SE GENERA ACOMPAÑAMIENTO ÁREA SGI": "Dayana Restrepo",
    "AREA": "SST",
    "ESTADO DE VISITA": "Ejecutada",
    "CANT. PERSONAL IMPACTADO": 3,
    "TEMAS ABORDADOS": "Capacitación ergonomia en la conducci+on - Pausa Activa, Socialización examenes - Tamizajes - Acompañamiento Osteomuscular Paola Galvis"
  },
  {
    "CLIENTE - LUGAR VISITA": "Jardin Botánico",
    "CIUDAD": "Medellín",
    "FECHA": 46139,
    "GESTOR LOGISTICO": "Yesid Carvajal",
    "EJECUTADA": "NO",
    "ACTIVIDAD A REALIZAR POR EL GESTOR": "Sin acompañamiento del gestor",
    "SE GENERA ACOMPAÑAMIENTO ÁREA SGI": "Dayana Restrepo ",
    "AREA": "SST",
    "ESTADO DE VISITA": "Sin Ejecutar",
    "CANT. PERSONAL IMPACTADO": 0,
    "TEMAS ABORDADOS": "No se coordina con gestor "
  },
  {
    "CLIENTE - LUGAR VISITA": "EPM - Hidroituango",
    "CIUDAD": "Ituango",
    "FECHA": 46139,
    "GESTOR LOGISTICO": "Carlos Franco",
    "EJECUTADA": "SI",
    "ACTIVIDAD A REALIZAR POR EL GESTOR": "Sin acompañamiento del gestor",
    "SE GENERA ACOMPAÑAMIENTO ÁREA SGI": "Daniela Vergara",
    "AREA": "SST",
    "ESTADO DE VISITA": "Ejecutada",
    "CANT. PERSONAL IMPACTADO": 28,
    "TEMAS ABORDADOS": "Tamizajes de embriaguz"
  },
  {
    "CLIENTE - LUGAR VISITA": "EPM - Hidroituango",
    "CIUDAD": "Ituango",
    "FECHA": 46140,
    "GESTOR LOGISTICO": "Carlos Franco",
    "EJECUTADA": "SI",
    "ACTIVIDAD A REALIZAR POR EL GESTOR": "Sin acompañamiento del gestor",
    "SE GENERA ACOMPAÑAMIENTO ÁREA SGI": "Dayana Restrepo ",
    "AREA": "SST",
    "ESTADO DE VISITA": "Ejecutada",
    "CANT. PERSONAL IMPACTADO": 34,
    "TEMAS ABORDADOS": "Cultura de la seguridad vial -prevención de la fatiga - comportamiento seguro - Pausas activas - Inspecciones de vehículos - Prevención de embriaguez - tamizajes"
  },
  {
    "CLIENTE - LUGAR VISITA": "Chemilab",
    "CIUDAD": "Medellín",
    "FECHA": 46142,
    "GESTOR LOGISTICO": "Edwin Aguirre",
    "EJECUTADA": "SI",
    "ACTIVIDAD A REALIZAR POR EL GESTOR": "Se cuenta con acompañamiento del gestor",
    "SE GENERA ACOMPAÑAMIENTO ÁREA SGI": "Dalila Anaya",
    "AREA": "SST",
    "ESTADO DE VISITA": "Ejecutada",
    "CANT. PERSONAL IMPACTADO": 2,
    "TEMAS ABORDADOS": "Divulgación estrategia de toma de conciencia  - Conducción preventiva - Tamizajes"
  },
  {
    "CLIENTE - LUGAR VISITA": "EPM - Hidroituango",
    "CIUDAD": "Ituango",
    "FECHA": 46141,
    "GESTOR LOGISTICO": "Carlos Franco",
    "EJECUTADA": "SI",
    "ACTIVIDAD A REALIZAR POR EL GESTOR": "Sin acompañamiento del gestor",
    "SE GENERA ACOMPAÑAMIENTO ÁREA SGI": "Dayana Restrepo ",
    "AREA": "SST",
    "ESTADO DE VISITA": "Ejecutada",
    "CANT. PERSONAL IMPACTADO": 20,
    "TEMAS ABORDADOS": "Socialización de examenes medicos - Pausas activas - Tamizajes de embriaguez - Momentos de seguridad"
  },
  {
    "CLIENTE - LUGAR VISITA": "Jardin Botánico",
    "CIUDAD": "Medellín",
    "FECHA": 46141,
    "GESTOR LOGISTICO": "Yesid Carvajal",
    "EJECUTADA": "SI",
    "ACTIVIDAD A REALIZAR POR EL GESTOR": "Se cuenta con acompañamiento del gestor",
    "SE GENERA ACOMPAÑAMIENTO ÁREA SGI": "Dalila Anaya ",
    "AREA": "SST",
    "ESTADO DE VISITA": "Ejecutada",
    "CANT. PERSONAL IMPACTADO": 21,
    "TEMAS ABORDADOS": "Reportes AT -Prevención de la embriaguez, pausas activas - condiciones inseguras - reporte de accidentes de trabajo y siniestros viales"
  },
  {
    "CLIENTE - LUGAR VISITA": "Chemilab",
    "CIUDAD": "Medellín",
    "FECHA": 46142,
    "GESTOR LOGISTICO": "Edwin Aguirre",
    "EJECUTADA": "SI",
    "ACTIVIDAD A REALIZAR POR EL GESTOR": "Se cuenta con acompañamiento del gestor",
    "SE GENERA ACOMPAÑAMIENTO ÁREA SGI": "Dayana Restrepo ",
    "AREA": "SST",
    "ESTADO DE VISITA": "Ejecutada",
    "CANT. PERSONAL IMPACTADO": 3,
    "TEMAS ABORDADOS": "Reportes AT -Prevención de la embriaguez, pausas activas - condiciones inseguras - reporte de accidentes de trabajo y siniestros viales - socialización de examenes - tamizajes"
  },
  {
    "CLIENTE - LUGAR VISITA": "CAH - Niñez (San Javier)",
    "CIUDAD": "Medellín",
    "FECHA": 46148,
    "GESTOR LOGISTICO": "Dayhana Sossa",
    "EJECUTADA": "SI",
    "ACTIVIDAD A REALIZAR POR EL GESTOR": "Se cuenta con acompañamiento del gestor",
    "SE GENERA ACOMPAÑAMIENTO ÁREA SGI": "Dalila Anaya",
    "AREA": "SST",
    "ESTADO DE VISITA": "Ejecutada",
    "CANT. PERSONAL IMPACTADO": 9,
    "TEMAS ABORDADOS": "Taller bateria humanoa - Acompañamiento pausa activa integral psicosocial Andrea Buritica y osteomuscular Paola Galvis"
  },
  {
    "CLIENTE - LUGAR VISITA": "EPM - Central Playas",
    "CIUDAD": "Guadalupe",
    "FECHA": 46162,
    "GESTOR LOGISTICO": "Carlos Franco",
    "EJECUTADA": "SI",
    "ACTIVIDAD A REALIZAR POR EL GESTOR": "Sin acompañamiento del gestor",
    "SE GENERA ACOMPAÑAMIENTO ÁREA SGI": "Daniela Vergara",
    "AREA": "SST",
    "ESTADO DE VISITA": "Ejecutada",
    "CANT. PERSONAL IMPACTADO": 6,
    "TEMAS ABORDADOS": "Prevención consumo alochol y sustancias - Tamizajes Embriaguez - Momentos de seguridad - PESV - lecciones aprendidas - Reportes accidentes - Identificación peligros y riesgos"
  },
  {
    "CLIENTE - LUGAR VISITA": "EPM - Central Playas",
    "CIUDAD": "Guadalupe",
    "FECHA": 46163,
    "GESTOR LOGISTICO": "Carlos Franco",
    "EJECUTADA": "SI",
    "ACTIVIDAD A REALIZAR POR EL GESTOR": "Sin acompañamiento del gestor",
    "SE GENERA ACOMPAÑAMIENTO ÁREA SGI": "Daniela Vergara",
    "AREA": "SST",
    "ESTADO DE VISITA": "Ejecutada",
    "CANT. PERSONAL IMPACTADO": 7,
    "TEMAS ABORDADOS": "Prevención consumo alochol y sustancias - Tamizajes Embriaguez - Momentos de seguridad - PESV - lecciones aprendidas - Reportes accidentes - Identificación peligros y riesgos"
  },
  {
    "CLIENTE - LUGAR VISITA": "Chemilab ",
    "CIUDAD": "Medellín",
    "FECHA": 46170,
    "GESTOR LOGISTICO": "Edwin Aguirre",
    "EJECUTADA": "SI",
    "ACTIVIDAD A REALIZAR POR EL GESTOR": "Sin acompañamiento del gestor",
    "SE GENERA ACOMPAÑAMIENTO ÁREA SGI": "Dalila Anaya ",
    "AREA": "SST",
    "ESTADO DE VISITA": "Ejecutada",
    "CANT. PERSONAL IMPACTADO": 2,
    "TEMAS ABORDADOS": "Prevención consumo alochol y sustancias - Tamizajes Embriaguez - Momentos de seguridad - PESV - lecciones aprendidas - Reportes accidentes - Identificación peligros y riesgos"
  },
  {
    "CLIENTE - LUGAR VISITA": "Jardin Botánico",
    "CIUDAD": "Medellín",
    "FECHA": 46176,
    "GESTOR LOGISTICO": "Juan David Blandon",
    "EJECUTADA": "SI",
    "ACTIVIDAD A REALIZAR POR EL GESTOR": "Se cuenta con acompañamiento del gestor",
    "SE GENERA ACOMPAÑAMIENTO ÁREA SGI": "Dayana Restrepo",
    "AREA": "SST",
    "ESTADO DE VISITA": "Ejecutada",
    "CANT. PERSONAL IMPACTADO": 16,
    "TEMAS ABORDADOS": "Tamizajes embriaguez"
  },
  {
    "CLIENTE - LUGAR VISITA": "Chemilab",
    "CIUDAD": "Medellín",
    "FECHA": 46190,
    "GESTOR LOGISTICO": "Edwin Aguirre",
    "EJECUTADA": "SI",
    "ACTIVIDAD A REALIZAR POR EL GESTOR": "Se cuenta con acompañamiento del gestor",
    "SE GENERA ACOMPAÑAMIENTO ÁREA SGI": "Dayana Restrepo",
    "AREA": "SST",
    "ESTADO DE VISITA": "Ejecutada",
    "CANT. PERSONAL IMPACTADO": 3,
    "TEMAS ABORDADOS": "Cuidado de la salud mental  acompañamiento psicosocial Andrea Buritica"
  },
  {
    "CLIENTE - LUGAR VISITA": "Jardin Botánico",
    "CIUDAD": "Medellín",
    "FECHA": 46190,
    "GESTOR LOGISTICO": "Juan David Blandon",
    "EJECUTADA": "SI",
    "ACTIVIDAD A REALIZAR POR EL GESTOR": "Se cuenta con acompañamiento del gestor",
    "SE GENERA ACOMPAÑAMIENTO ÁREA SGI": "Dayana Restrepo",
    "AREA": "SST",
    "ESTADO DE VISITA": "Ejecutada",
    "CANT. PERSONAL IMPACTADO": 16,
    "TEMAS ABORDADOS": "Cuidado de la salud mental  acompañamiento psicosocial Andrea Buritica - Tamizajes prevención del consumo de alcohol y susntancias"
  },
  {
    "CLIENTE - LUGAR VISITA": "CAH - Niñez (Universidad)",
    "CIUDAD": "Medellín",
    "FECHA": 46191,
    "GESTOR LOGISTICO": "Dayhana Sossa",
    "EJECUTADA": "SI",
    "ACTIVIDAD A REALIZAR POR EL GESTOR": "Se cuenta con acompañamiento del gestor",
    "SE GENERA ACOMPAÑAMIENTO ÁREA SGI": "Dalila Anaya",
    "AREA": "SST",
    "ESTADO DE VISITA": "Ejecutada",
    "CANT. PERSONAL IMPACTADO": 8,
    "TEMAS ABORDADOS": "Se realiza tamizaje de alcohol y actividad prevención del Riesgo Psicosocial  Andrea Buritica"
  },
  {
    "CLIENTE - LUGAR VISITA": "Jardin Botánico",
    "CIUDAD": "Medellín",
    "FECHA": 46191,
    "GESTOR LOGISTICO": "Edinson Saldarriaga",
    "EJECUTADA": "SI",
    "ACTIVIDAD A REALIZAR POR EL GESTOR": "Se cuenta con acompañamiento del gestor",
    "SE GENERA ACOMPAÑAMIENTO ÁREA SGI": "Angy Arzuza",
    "AREA": "SST",
    "ESTADO DE VISITA": "Ejecutada",
    "CANT. PERSONAL IMPACTADO": 14,
    "TEMAS ABORDADOS": "Se realiza tamizaje de alcohol"
  },
  {
    "CLIENTE - LUGAR VISITA": "Sura Industruales",
    "CIUDAD": "Medellín",
    "FECHA": 46191,
    "GESTOR LOGISTICO": "Hawer Murcia",
    "EJECUTADA": "SI",
    "ACTIVIDAD A REALIZAR POR EL GESTOR": "Se cuenta con acompañamiento del gestor",
    "SE GENERA ACOMPAÑAMIENTO ÁREA SGI": "Dayana Restrepo",
    "AREA": "SST",
    "ESTADO DE VISITA": "Ejecutada",
    "CANT. PERSONAL IMPACTADO": 40,
    "TEMAS ABORDADOS": "Se realiza tamizaje de alcohol"
  },
  {
    "CLIENTE - LUGAR VISITA": "Flota propia",
    "CIUDAD": "Medellín",
    "FECHA": 46191,
    "GESTOR LOGISTICO": "Jonathan Giraldo",
    "EJECUTADA": "SI",
    "ACTIVIDAD A REALIZAR POR EL GESTOR": "Sin acompañamiento del gestor",
    "SE GENERA ACOMPAÑAMIENTO ÁREA SGI": "Daniela Vergara",
    "AREA": "SST",
    "ESTADO DE VISITA": "Ejecutada",
    "CANT. PERSONAL IMPACTADO": 13,
    "TEMAS ABORDADOS": "Se realiza tamizaje de alcohol"
  },
  {
    "CLIENTE - LUGAR VISITA": "CAH - Niñez (San Javier)",
    "CIUDAD": "Medellín",
    "FECHA": 46197,
    "GESTOR LOGISTICO": "Dayhana Sossa",
    "EJECUTADA": "SI",
    "ACTIVIDAD A REALIZAR POR EL GESTOR": "Se cuenta con acompañamiento del gestor",
    "SE GENERA ACOMPAÑAMIENTO ÁREA SGI": "Dalila Anaya  ",
    "AREA": "SST",
    "ESTADO DE VISITA": "Ejecutada",
    "CANT. PERSONAL IMPACTADO": 8,
    "TEMAS ABORDADOS": "Se realiza tamizaje de alcohol"
  },
  {
    "CLIENTE - LUGAR VISITA": "Telemedellin ",
    "CIUDAD": "Medellín",
    "FECHA": 46197,
    "GESTOR LOGISTICO": "Julieth Higuita",
    "EJECUTADA": "SI",
    "ACTIVIDAD A REALIZAR POR EL GESTOR": "Se cuenta con acompañamiento del gestor",
    "SE GENERA ACOMPAÑAMIENTO ÁREA SGI": "Daniela Vergara",
    "AREA": "SST",
    "ESTADO DE VISITA": "Ejecutada",
    "CANT. PERSONAL IMPACTADO": 6,
    "TEMAS ABORDADOS": "Se realiza tamizaje de alcohol"
  },
  {
    "CLIENTE - LUGAR VISITA": "Sura Industruales",
    "CIUDAD": "Medellín",
    "FECHA": 46197,
    "GESTOR LOGISTICO": "Edwin Jimenez",
    "EJECUTADA": "SI",
    "ACTIVIDAD A REALIZAR POR EL GESTOR": "Se cuenta con acompañamiento del gestor",
    "SE GENERA ACOMPAÑAMIENTO ÁREA SGI": "Angy Arzuza",
    "AREA": "SST",
    "ESTADO DE VISITA": "Ejecutada",
    "CANT. PERSONAL IMPACTADO": 35,
    "TEMAS ABORDADOS": "Se realiza tamizaje de alcohol"
  }
]